inventree_ss_batch_number_generator-0.2.9.dist-info/licenses/LICENSE
ss_batch_number_generator/__init__.py
ss_batch_number_generator/core.py
inventree_ss_batch_number_generator-0.2.9.dist-info/METADATA
inventree_ss_batch_number_generator-0.2.9.dist-info/WHEEL
inventree_ss_batch_number_generator-0.2.9.dist-info/entry_points.txt
inventree_ss_batch_number_generator-0.2.9.dist-info/top_level.txt
inventree_ss_batch_number_generator-0.2.9.dist-info/RECORD
