Metadata-Version: 2.4
Name: inventree-ss-batch-number-generator
Version: 0.2.9
Summary: Plugin to generate unique batch numbers
Home-page: https://www.smartsentry.co.uk
Author: Rob Kettridge
Author-email: rob.kettridge@smartsentry.co.uk
License: MIT
Keywords: inventree plugin
Classifier: Programming Language :: Python :: 3
Classifier: Operating System :: OS Independent
Classifier: Framework :: InvenTree
Requires-Python: >=3.9
License-File: LICENSE
Requires-Dist: inventree
Dynamic: author
Dynamic: author-email
Dynamic: classifier
Dynamic: description
Dynamic: description-content-type
Dynamic: home-page
Dynamic: keywords
Dynamic: license
Dynamic: license-file
Dynamic: requires-dist
Dynamic: requires-python
Dynamic: summary
